.gitignore
.gitlab-ci.yml
.install-neurodamus.sh
AUTHORS.txt
CHANGELOG.rst
LICENSE.txt
Makefile
README.rst
pyproject.toml
setup.py
tox.ini
.github/workflows/sdist.yml
.github/workflows/tox.yml
doc/Makefile
doc/source/changelog.rst
doc/source/conf.py
doc/source/cookbook.rst
doc/source/cv_validation.rst
doc/source/files.rst
doc/source/index.rst
doc/source/install.rst
doc/source/methodology.rst
doc/source/tutorial.rst
doc/source/images/a5526-a24711.png
psp_validation/__init__.py
psp_validation/cli.py
psp_validation/features.py
psp_validation/pathways.py
psp_validation/persistencyutils.py
psp_validation/plot.py
psp_validation/psp.py
psp_validation/simulation.py
psp_validation/trace_filters.py
psp_validation/utils.py
psp_validation/version.py
psp_validation.egg-info/PKG-INFO
psp_validation.egg-info/SOURCES.txt
psp_validation.egg-info/dependency_links.txt
psp_validation.egg-info/entry_points.txt
psp_validation.egg-info/requires.txt
psp_validation.egg-info/top_level.txt
psp_validation/cv_validation/__init__.py
psp_validation/cv_validation/analyze_traces.py
psp_validation/cv_validation/calibrate_nrrp.py
psp_validation/cv_validation/cli.py
psp_validation/cv_validation/ou_generator.py
psp_validation/cv_validation/plots.py
psp_validation/cv_validation/setsim.py
psp_validation/cv_validation/simulator.py
psp_validation/cv_validation/utils.py
sbatch/run-psp-parallel.sbatch.template
sbatch/run-psp.sbatch
tests/__init__.py
tests/test_cli.py
tests/test_features.py
tests/test_pathway.py
tests/test_psp.py
tests/test_simulation.py
tests/test_trace_filters.py
tests/test_utils.py
tests/utils.py
tests/cv_validation/__init__.py
tests/cv_validation/test_analyze_traces.py
tests/cv_validation/test_calibrate_nrrp.py
tests/cv_validation/test_cli.py
tests/cv_validation/test_ou_generator.py
tests/cv_validation/test_simulator.py
tests/cv_validation/input_data/SP_PVBC-SP_PC.yaml
tests/cv_validation/input_data/pairs.csv
tests/cv_validation/input_data/targets.yaml
tests/input_data/example_trace.txt
tests/input_data/pathway.yaml
tests/input_data/small-traces.h5
tests/input_data/simple/circuit_config.json
tests/input_data/simple/simulation_config.json
tests/input_data/simple/user.target
